.bumpversion.cfg
.cookiecutterrc
.coveragerc
.editorconfig
.travis.yml
AUTHORS.rst
CHANGELOG.rst
CONTRIBUTING.rst
LICENSE
MANIFEST.in
README.rst
setup.cfg
setup.py
tox.ini
ci/bootstrap.py
ci/templates/.travis.yml
docs/authors.rst
docs/changelog.rst
docs/conf.py
docs/contributing.rst
docs/index.rst
docs/installation.rst
docs/readme.rst
docs/requirements.txt
docs/spelling_wordlist.txt
docs/usage.rst
docs/reference/index.rst
docs/reference/textworld_remote_env.rst
src/textworld_remote_env/__init__.py
src/textworld_remote_env/__main__.py
src/textworld_remote_env/client.py
src/textworld_remote_env/client_old.py
src/textworld_remote_env/message_broker.py
src/textworld_remote_env/messages.py
src/textworld_remote_env/service.py
src/textworld_remote_env/state.py
src/textworld_remote_env.egg-info/PKG-INFO
src/textworld_remote_env.egg-info/SOURCES.txt
src/textworld_remote_env.egg-info/dependency_links.txt
src/textworld_remote_env.egg-info/entry_points.txt
src/textworld_remote_env.egg-info/not-zip-safe
src/textworld_remote_env.egg-info/requires.txt
src/textworld_remote_env.egg-info/top_level.txt
tests/test_textworld_remote_env.py